shfy/__init__.py
shfy/shfy.py
shfy/shfy_completion.py
shfy-0.2.0.dist-info/LICENSE
shfy-0.2.0.dist-info/METADATA
shfy-0.2.0.dist-info/WHEEL
shfy-0.2.0.dist-info/entry_points.txt
shfy-0.2.0.dist-info/top_level.txt
shfy-0.2.0.dist-info/RECORD
