Metadata-Version: 2.1
Name: shfy
Version: 0.2.0
Summary: Shfy (Shellify) provides AI-powered assistance, suggestions, and automation to simplify and streamline command line tasks.
Home-page: https://github.com/filipgrano/shfy
Author: Filip Granö
Author-email: filip-accounts@grano.me
License: UNKNOWN
Platform: UNKNOWN
Classifier: Development Status :: 4 - Beta
Classifier: Intended Audience :: Developers
Classifier: License :: OSI Approved :: BSD License
Classifier: Programming Language :: Python :: 3
Classifier: Programming Language :: Python :: 3.7
Classifier: Programming Language :: Python :: 3.8
Classifier: Programming Language :: Python :: 3.9
Classifier: Programming Language :: Python :: 3.10
Classifier: Programming Language :: Python :: 3.11
Classifier: Programming Language :: Python :: 3.12
Classifier: Programming Language :: Python :: 3.13
Requires-Python: >=3.7
Requires-Dist: openai >=1.0.0
Requires-Dist: PyYAML
Requires-Dist: types-PyYAML
